<?xml version="1.0" encoding="UTF-8"?>
<data>
	<title><![CDATA[60 NOUVEAUX LOGEMENTS A L’ISLE D’ABEAU]]></title>
	<text><![CDATA[Projet d'aménagement d'un terrain escarpé de la ville en quartier de 60 logements. Le projet s'inspire des chalets locaux qui s'adaptaient au terrain : une base en pierre qui suit la pente d'un terrain surmontée d'une charpente bois. Le projet réinterprète ce schéma : les espaces à vivre (salons, salle à manger, etc.) de tous les logements se trouvent sous une large dalle végétalisée qui rejoint les pentes du terrain. Sur ces grandes bandes végétales sont posés des modules de bois qui accueillent les espaces secondaires des logements (chambres, sdb, etc.)]]></text>
	<infos><![CDATA[LIEU : quartier de Champouland, ville de l'Isle d'Abeau<br/>ORGANISATEUR : Europan 10<br/>MAITRISE D'OEUVRE : Pierre-Antoine GRUAU, Julien Fieulaine, Michael BELOLO<br/>PROGRAMME : 60 logements, coulée verte<br/>SURFACE :6 hectares]]></infos>
	<photos>
		<pic>01-VUE.jpg</pic>
		<pic>02-PLAN-MASSE.jpg</pic>
		<pic>03-PLANS.jpg</pic>
		<pic>04-PLANS.jpg</pic>
		<pic>05-COUPE.jpg</pic>
	</photos>
</data>
